{
  "meta": {
    "data_source": "real",
    "params": {
      "adx_max": 25,
      "k": 2.5,
      "n": 20,
      "stop_k": 2.5
    },
    "account_balance": 100000.0,
    "risk_per_trade": 0.02,
    "max_leverage": 20.0,
    "generated_at": "2026-07-07T23:29:50.674514"
  },
  "pairs": {
    "USDJPY": {
      "pair": "USDJPY",
      "current_equity": 2801971.3573804037,
      "today_signal": null,
      "open_position": null,
      "yesterday_result": null,
      "recent_trades": [
        {
          "entry_date": "2023-10-27T00:00:00",
          "exit_date": "2023-10-30T00:00:00",
          "direction": -1,
          "entry_price": 150.36599731445312,
          "exit_price": 149.41690063476562,
          "stop_price": 150.66025044659068,
          "target_price": 149.41690063476562,
          "leverage": 10.220179898996694,
          "pnl_pct": 0.0631494844549809,
          "reason": "target",
          "hold_days": 3
        },
        {
          "entry_date": "2023-11-01T00:00:00",
          "exit_date": "2023-11-03T00:00:00",
          "direction": -1,
          "entry_price": 151.29400634765625,
          "exit_price": 149.44100036621094,
          "stop_price": 150.7895682207519,
          "target_price": 149.44100036621094,
          "leverage": 5.998515904264511,
          "pnl_pct": 0.07267515612644745,
          "reason": "target",
          "hold_days": 2
        },
        {
          "entry_date": "2023-11-13T00:00:00",
          "exit_date": "2023-11-14T00:00:00",
          "direction": -1,
          "entry_price": 151.468994140625,
          "exit_price": 151.53740613848197,
          "stop_price": 151.53740613848197,
          "target_price": 150.08355026245118,
          "leverage": 20.0,
          "pnl_pct": -0.0116739400507126,
          "reason": "stop",
          "hold_days": 1
        },
        {
          "entry_date": "2023-11-14T00:00:00",
          "exit_date": "2023-11-17T00:00:00",
          "direction": -1,
          "entry_price": 151.64599609375,
          "exit_price": 150.17870025634767,
          "stop_price": 151.7828306872955,
          "target_price": 150.17870025634767,
          "leverage": 20.0,
          "pnl_pct": 0.19087821303341113,
          "reason": "target",
          "hold_days": 3
        },
        {
          "entry_date": "2023-11-21T00:00:00",
          "exit_date": "2023-11-22T00:00:00",
          "direction": 1,
          "entry_price": 148.36199951171875,
          "exit_price": 148.71180919285166,
          "stop_price": 148.71180919285166,
          "target_price": 150.4402992248535,
          "leverage": 8.482441025144096,
          "pnl_pct": 0.018856521069672682,
          "reason": "stop",
          "hold_days": 1
        },
        {
          "entry_date": "2023-11-22T00:00:00",
          "exit_date": "2023-11-28T00:00:00",
          "direction": 1,
          "entry_price": 148.15199279785156,
          "exit_price": 148.3289423830386,
          "stop_price": 148.3289423830386,
          "target_price": 150.3699493408203,
          "leverage": 16.74510766908645,
          "pnl_pct": 0.017739469128581403,
          "reason": "stop",
          "hold_days": 6
        },
        {
          "entry_date": "2023-11-29T00:00:00",
          "exit_date": "2023-11-30T00:00:00",
          "direction": 1,
          "entry_price": 147.06300354003906,
          "exit_price": 147.62299733207286,
          "stop_price": 147.62299733207286,
          "target_price": 150.17534866333008,
          "leverage": 5.252308351702739,
          "pnl_pct": 0.01928570636730226,
          "reason": "stop",
          "hold_days": 1
        },
        {
          "entry_date": "2023-11-30T00:00:00",
          "exit_date": "2023-12-01T00:00:00",
          "direction": 1,
          "entry_price": 147.03900146484375,
          "exit_price": 146.98540658412472,
          "stop_price": 146.98540658412472,
          "target_price": 149.96379852294922,
          "leverage": 20.0,
          "pnl_pct": -0.0100102530601894,
          "reason": "stop",
          "hold_days": 1
        },
        {
          "entry_date": "2024-02-14T00:00:00",
          "exit_date": "2024-02-15T00:00:00",
          "direction": -1,
          "entry_price": 150.7239990234375,
          "exit_price": 149.85546559386026,
          "stop_price": 149.85546559386026,
          "target_price": 148.03100204467773,
          "leverage": 3.47077024074485,
          "pnl_pct": 0.019539453535836037,
          "reason": "stop",
          "hold_days": 1
        },
        {
          "entry_date": "2024-06-17T00:00:00",
          "exit_date": "2024-06-18T00:00:00",
          "direction": -1,
          "entry_price": 157.54600524902344,
          "exit_price": 158.16787410783016,
          "stop_price": 158.16787410783016,
          "target_price": 156.6250991821289,
          "leverage": 5.066856235616369,
          "pnl_pct": -0.020643222432407286,
          "reason": "stop",
          "hold_days": 1
        },
        {
          "entry_date": "2024-06-21T00:00:00",
          "exit_date": "2024-06-24T00:00:00",
          "direction": -1,
          "entry_price": 158.93099975585938,
          "exit_price": 158.70860850113925,
          "stop_price": 158.70860850113925,
          "target_price": 156.92489929199218,
          "leverage": 14.29291812359014,
          "pnl_pct": 0.0182013681225757,
          "reason": "stop",
          "hold_days": 3
        },
        {
          "entry_date": "2024-06-24T00:00:00",
          "exit_date": "2024-06-25T00:00:00",
          "direction": -1,
          "entry_price": 159.86099243164062,
          "exit_price": 159.11531663876607,
          "stop_price": 159.11531663876607,
          "target_price": 157.02279891967774,
          "leverage": 4.287680891862746,
          "pnl_pct": 0.019463573842919028,
          "reason": "stop",
          "hold_days": 1
        },
        {
          "entry_date": "2024-10-03T00:00:00",
          "exit_date": "2024-10-04T00:00:00",
          "direction": -1,
          "entry_price": 146.58200073242188,
          "exit_price": 145.658048042049,
          "stop_price": 145.658048042049,
          "target_price": 142.92294921875,
          "leverage": 3.1729330356355105,
          "pnl_pct": 0.019567077401074974,
          "reason": "stop",
          "hold_days": 1
        },
        {
          "entry_date": "2024-10-07T00:00:00",
          "exit_date": "2024-10-08T00:00:00",
          "direction": -1,
          "entry_price": 148.82000732421875,
          "exit_price": 147.21265509476692,
          "stop_price": 147.21265509476692,
          "target_price": 143.2581985473633,
          "leverage": 1.851741075756268,
          "pnl_pct": 0.019751143531162165,
          "reason": "stop",
          "hold_days": 1
        },
        {
          "entry_date": "2025-06-24T00:00:00",
          "exit_date": "2025-06-26T00:00:00",
          "direction": -1,
          "entry_price": 145.92799377441406,
          "exit_price": 144.23725128173828,
          "stop_price": 146.72817044296607,
          "target_price": 144.23725128173828,
          "leverage": 3.647394369508002,
          "pnl_pct": 0.04175934036415062,
          "reason": "target",
          "hold_days": 2
        },
        {
          "entry_date": "2025-07-09T00:00:00",
          "exit_date": "2025-07-10T00:00:00",
          "direction": -1,
          "entry_price": 146.8489990234375,
          "exit_price": 146.69665817384083,
          "stop_price": 146.69665817384083,
          "target_price": 144.68140106201173,
          "leverage": 19.279004864713354,
          "pnl_pct": 0.017374308985022582,
          "reason": "stop",
          "hold_days": 1
        },
        {
          "entry_date": "2025-07-10T00:00:00",
          "exit_date": "2025-07-11T00:00:00",
          "direction": -1,
          "entry_price": 146.11399841308594,
          "exit_price": 147.11833376563112,
          "stop_price": 147.11833376563112,
          "target_price": 144.7819511413574,
          "leverage": 2.909665542347072,
          "pnl_pct": -0.020398273344641633,
          "reason": "stop",
          "hold_days": 1
        },
        {
          "entry_date": "2025-07-14T00:00:00",
          "exit_date": "2025-07-15T00:00:00",
          "direction": -1,
          "entry_price": 147.2949981689453,
          "exit_price": 147.36411501173015,
          "stop_price": 147.36411501173015,
          "target_price": 145.0322006225586,
          "leverage": 20.0,
          "pnl_pct": -0.012100457434762447,
          "reason": "stop",
          "hold_days": 1
        },
        {
          "entry_date": "2025-07-16T00:00:00",
          "exit_date": "2025-07-17T00:00:00",
          "direction": -1,
          "entry_price": 148.76100158691406,
          "exit_price": 148.26082720352073,
          "stop_price": 148.26082720352073,
          "target_price": 145.34555053710938,
          "leverage": 5.948365471165317,
          "pnl_pct": 0.019200278916152638,
          "reason": "stop",
          "hold_days": 1
        },
        {
          "entry_date": "2025-07-17T00:00:00",
          "exit_date": "2025-07-30T00:00:00",
          "direction": -1,
          "entry_price": 148.0030059814453,
          "exit_price": 148.9738351086703,
          "stop_price": 148.9738351086703,
          "target_price": 145.51480026245116,
          "leverage": 3.0490021741415236,
          "pnl_pct": -0.020412018952442598,
          "reason": "stop",
          "hold_days": 13
        },
        {
          "entry_date": "2025-09-10T00:00:00",
          "exit_date": "2025-09-11T00:00:00",
          "direction": 1,
          "entry_price": 147.39199829101562,
          "exit_price": 147.62904891967773,
          "stop_price": 146.39166814657008,
          "target_price": 147.62904891967773,
          "leverage": 2.9468670740240737,
          "pnl_pct": 0.0043395798850470405,
          "reason": "target",
          "hold_days": 1
        },
        {
          "entry_date": "2025-09-26T00:00:00",
          "exit_date": "2025-09-29T00:00:00",
          "direction": -1,
          "entry_price": 149.86099243164062,
          "exit_price": 149.11681107790892,
          "stop_price": 149.11681107790892,
          "target_price": 147.60180053710937,
          "leverage": 4.027539568954832,
          "pnl_pct": 0.019462496610545003,
          "reason": "stop",
          "hold_days": 3
        },
        {
          "entry_date": "2025-10-07T00:00:00",
          "exit_date": "2025-10-08T00:00:00",
          "direction": -1,
          "entry_price": 150.33099365234375,
          "exit_price": 150.14394567313784,
          "stop_price": 150.14394567313784,
          "target_price": 147.87574996948243,
          "leverage": 16.074056965549982,
          "pnl_pct": 0.017861511245948,
          "reason": "stop",
          "hold_days": 1
        },
        {
          "entry_date": "2025-10-08T00:00:00",
          "exit_date": "2025-10-09T00:00:00",
          "direction": -1,
          "entry_price": 152.05099487304688,
          "exit_price": 150.63353312597297,
          "stop_price": 150.63353312597297,
          "target_price": 148.02409973144532,
          "leverage": 2.145398211795546,
          "pnl_pct": 0.019717805435789906,
          "reason": "stop",
          "hold_days": 1
        },
        {
          "entry_date": "2025-12-22T00:00:00",
          "exit_date": "2025-12-23T00:00:00",
          "direction": -1,
          "entry_price": 157.60899353027344,
          "exit_price": 155.80309829711913,
          "stop_price": 157.26499797816612,
          "target_price": 155.80309829711913,
          "leverage": 9.163432059790374,
          "pnl_pct": 0.10383246075211801,
          "reason": "target",
          "hold_days": 1
        },
        {
          "entry_date": "2026-01-12T00:00:00",
          "exit_date": "2026-01-13T00:00:00",
          "direction": -1,
          "entry_price": 158.1230010986328,
          "exit_price": 157.97458297315885,
          "stop_price": 157.97458297315885,
          "target_price": 156.22319869995118,
          "leverage": 20.0,
          "pnl_pct": 0.016242814085455283,
          "reason": "stop",
          "hold_days": 1
        },
        {
          "entry_date": "2026-01-14T00:00:00",
          "exit_date": "2026-01-15T00:00:00",
          "direction": -1,
          "entry_price": 159.1790008544922,
          "exit_price": 158.6179007725835,
          "stop_price": 158.6179007725835,
          "target_price": 156.46209869384765,
          "leverage": 5.673818485750987,
          "pnl_pct": 0.019287114700394747,
          "reason": "stop",
          "hold_days": 1
        },
        {
          "entry_date": "2026-01-15T00:00:00",
          "exit_date": "2026-01-26T00:00:00",
          "direction": -1,
          "entry_price": 158.43600463867188,
          "exit_price": 156.62664871215821,
          "stop_price": 159.2116039075472,
          "target_price": 156.62664871215821,
          "leverage": 4.085511964662328,
          "pnl_pct": 0.046141248408044226,
          "reason": "target",
          "hold_days": 11
        },
        {
          "entry_date": "2026-04-20T00:00:00",
          "exit_date": "2026-04-21T00:00:00",
          "direction": 1,
          "entry_price": 159.1529998779297,
          "exit_price": 159.1987503051758,
          "stop_price": 157.95795394817287,
          "target_price": 159.1987503051758,
          "leverage": 2.6635461602771415,
          "pnl_pct": 0.0004309529300073874,
          "reason": "target",
          "hold_days": 1
        },
        {
          "entry_date": "2026-04-30T00:00:00",
          "exit_date": "2026-05-01T00:00:00",
          "direction": -1,
          "entry_price": 160.1929931640625,
          "exit_price": 159.24500045776367,
          "stop_price": 160.18201521454748,
          "target_price": 159.24500045776367,
          "leverage": 20.0,
          "pnl_pct": 0.11585933791104397,
          "reason": "target",
          "hold_days": 1
        }
      ],
      "equity_curve": [
        {
          "date": "2011-07-31",
          "equity": 100000.0
        },
        {
          "date": "2011-08-31",
          "equity": 100000.0
        },
        {
          "date": "2011-09-30",
          "equity": 99725.82973263462
        },
        {
          "date": "2011-10-31",
          "equity": 99725.82973263462
        },
        {
          "date": "2011-11-30",
          "equity": 99725.82973263462
        },
        {
          "date": "2011-12-31",
          "equity": 99725.82973263462
        },
        {
          "date": "2012-01-31",
          "equity": 101629.74050154952
        },
        {
          "date": "2012-02-29",
          "equity": 104596.17796529931
        },
        {
          "date": "2012-03-31",
          "equity": 104596.17796529931
        },
        {
          "date": "2012-04-30",
          "equity": 104337.98366914676
        },
        {
          "date": "2012-05-31",
          "equity": 101939.37832679054
        },
        {
          "date": "2012-06-30",
          "equity": 115825.95785179503
        },
        {
          "date": "2012-07-31",
          "equity": 115292.8274523775
        },
        {
          "date": "2012-08-31",
          "equity": 115292.8274523775
        },
        {
          "date": "2012-09-30",
          "equity": 128648.21028596931
        },
        {
          "date": "2012-10-31",
          "equity": 128648.21028596931
        },
        {
          "date": "2012-11-30",
          "equity": 128648.21028596931
        },
        {
          "date": "2012-12-31",
          "equity": 128648.21028596931
        },
        {
          "date": "2013-01-31",
          "equity": 128648.21028596931
        },
        {
          "date": "2013-02-28",
          "equity": 128648.21028596931
        },
        {
          "date": "2013-03-31",
          "equity": 131174.09093067053
        },
        {
          "date": "2013-04-30",
          "equity": 131174.09093067053
        },
        {
          "date": "2013-05-31",
          "equity": 131402.5183402044
        },
        {
          "date": "2013-06-30",
          "equity": 131402.5183402044
        },
        {
          "date": "2013-07-31",
          "equity": 128628.66187290229
        },
        {
          "date": "2013-08-31",
          "equity": 128230.35235298795
        },
        {
          "date": "2013-09-30",
          "equity": 125409.75696586784
        },
        {
          "date": "2013-10-31",
          "equity": 125409.75696586784
        },
        {
          "date": "2013-11-30",
          "equity": 125485.7835179646
        },
        {
          "date": "2013-12-31",
          "equity": 125485.7835179646
        },
        {
          "date": "2014-01-31",
          "equity": 127944.32304666637
        },
        {
          "date": "2014-02-28",
          "equity": 127944.32304666637
        },
        {
          "date": "2014-03-31",
          "equity": 151351.0462188106
        },
        {
          "date": "2014-04-30",
          "equity": 151351.0462188106
        },
        {
          "date": "2014-05-31",
          "equity": 150989.5325251014
        },
        {
          "date": "2014-06-30",
          "equity": 176879.32381538168
        },
        {
          "date": "2014-07-31",
          "equity": 194907.32867612378
        },
        {
          "date": "2014-08-31",
          "equity": 198049.83712241694
        },
        {
          "date": "2014-09-30",
          "equity": 198049.83712241694
        },
        {
          "date": "2014-10-31",
          "equity": 198049.83712241694
        },
        {
          "date": "2014-11-30",
          "equity": 198049.83712241694
        },
        {
          "date": "2014-12-31",
          "equity": 198049.83712241694
        },
        {
          "date": "2015-01-31",
          "equity": 201179.10521308644
        },
        {
          "date": "2015-02-28",
          "equity": 201179.10521308644
        },
        {
          "date": "2015-03-31",
          "equity": 201179.10521308644
        },
        {
          "date": "2015-04-30",
          "equity": 201179.10521308644
        },
        {
          "date": "2015-05-31",
          "equity": 211330.7185535144
        },
        {
          "date": "2015-06-30",
          "equity": 211330.7185535144
        },
        {
          "date": "2015-07-31",
          "equity": 215475.49333128493
        },
        {
          "date": "2015-08-31",
          "equity": 255545.52343553744
        },
        {
          "date": "2015-09-30",
          "equity": 255545.52343553744
        },
        {
          "date": "2015-10-31",
          "equity": 256166.90344500032
        },
        {
          "date": "2015-11-30",
          "equity": 256166.90344500032
        },
        {
          "date": "2015-12-31",
          "equity": 266146.6849134742
        },
        {
          "date": "2016-01-31",
          "equity": 266146.6849134742
        },
        {
          "date": "2016-02-29",
          "equity": 260237.8590448259
        },
        {
          "date": "2016-03-31",
          "equity": 317744.7137696618
        },
        {
          "date": "2016-04-30",
          "equity": 317744.7137696618
        },
        {
          "date": "2016-05-31",
          "equity": 317744.7137696618
        },
        {
          "date": "2016-06-30",
          "equity": 317744.7137696618
        },
        {
          "date": "2016-07-31",
          "equity": 317744.7137696618
        },
        {
          "date": "2016-08-31",
          "equity": 317744.7137696618
        },
        {
          "date": "2016-09-30",
          "equity": 317744.7137696618
        },
        {
          "date": "2016-10-31",
          "equity": 306691.4352953172
        },
        {
          "date": "2016-11-30",
          "equity": 324784.9003420392
        },
        {
          "date": "2016-12-31",
          "equity": 324784.9003420392
        },
        {
          "date": "2017-01-31",
          "equity": 324784.9003420392
        },
        {
          "date": "2017-02-28",
          "equity": 324784.9003420392
        },
        {
          "date": "2017-03-31",
          "equity": 329135.764020377
        },
        {
          "date": "2017-04-30",
          "equity": 329135.764020377
        },
        {
          "date": "2017-05-31",
          "equity": 329135.764020377
        },
        {
          "date": "2017-06-30",
          "equity": 329135.764020377
        },
        {
          "date": "2017-07-31",
          "equity": 333587.10104302695
        },
        {
          "date": "2017-08-31",
          "equity": 333587.10104302695
        },
        {
          "date": "2017-09-30",
          "equity": 398700.63838919054
        },
        {
          "date": "2017-10-31",
          "equity": 404870.62627508934
        },
        {
          "date": "2017-11-30",
          "equity": 394092.8481227969
        },
        {
          "date": "2017-12-31",
          "equity": 394092.8481227969
        },
        {
          "date": "2018-01-31",
          "equity": 401745.89497493504
        },
        {
          "date": "2018-02-28",
          "equity": 401745.89497493504
        },
        {
          "date": "2018-03-31",
          "equity": 511191.6984330036
        },
        {
          "date": "2018-04-30",
          "equity": 511191.6984330036
        },
        {
          "date": "2018-05-31",
          "equity": 511191.6984330036
        },
        {
          "date": "2018-06-30",
          "equity": 511191.6984330036
        },
        {
          "date": "2018-07-31",
          "equity": 498391.82657622633
        },
        {
          "date": "2018-08-31",
          "equity": 498391.82657622633
        },
        {
          "date": "2018-09-30",
          "equity": 470352.6674741651
        },
        {
          "date": "2018-10-31",
          "equity": 470352.6674741651
        },
        {
          "date": "2018-11-30",
          "equity": 470352.6674741651
        },
        {
          "date": "2018-12-31",
          "equity": 460068.884057563
        },
        {
          "date": "2019-01-31",
          "equity": 460068.884057563
        },
        {
          "date": "2019-02-28",
          "equity": 460068.884057563
        },
        {
          "date": "2019-03-31",
          "equity": 460068.884057563
        },
        {
          "date": "2019-04-30",
          "equity": 460068.884057563
        },
        {
          "date": "2019-05-31",
          "equity": 460068.884057563
        },
        {
          "date": "2019-06-30",
          "equity": 460068.884057563
        },
        {
          "date": "2019-07-31",
          "equity": 460068.884057563
        },
        {
          "date": "2019-08-31",
          "equity": 459015.2489193721
        },
        {
          "date": "2019-09-30",
          "equity": 456123.0039179803
        },
        {
          "date": "2019-10-31",
          "equity": 456123.0039179803
        },
        {
          "date": "2019-11-30",
          "equity": 456123.0039179803
        },
        {
          "date": "2019-12-31",
          "equity": 456123.0039179803
        },
        {
          "date": "2020-01-31",
          "equity": 456123.0039179803
        },
        {
          "date": "2020-02-29",
          "equity": 456123.0039179803
        },
        {
          "date": "2020-03-31",
          "equity": 456123.0039179803
        },
        {
          "date": "2020-04-30",
          "equity": 456123.0039179803
        },
        {
          "date": "2020-05-31",
          "equity": 456123.0039179803
        },
        {
          "date": "2020-06-30",
          "equity": 456123.0039179803
        },
        {
          "date": "2020-07-31",
          "equity": 464950.14919544786
        },
        {
          "date": "2020-08-31",
          "equity": 464950.14919544786
        },
        {
          "date": "2020-09-30",
          "equity": 464950.14919544786
        },
        {
          "date": "2020-10-31",
          "equity": 464950.14919544786
        },
        {
          "date": "2020-11-30",
          "equity": 464950.14919544786
        },
        {
          "date": "2020-12-31",
          "equity": 465454.96215916536
        },
        {
          "date": "2021-01-31",
          "equity": 465454.96215916536
        },
        {
          "date": "2021-02-28",
          "equity": 465957.9200331466
        },
        {
          "date": "2021-03-31",
          "equity": 465957.9200331466
        },
        {
          "date": "2021-04-30",
          "equity": 465957.9200331466
        },
        {
          "date": "2021-05-31",
          "equity": 469693.78797133453
        },
        {
          "date": "2021-06-30",
          "equity": 535309.519520881
        },
        {
          "date": "2021-07-31",
          "equity": 621116.3025718576
        },
        {
          "date": "2021-08-31",
          "equity": 621116.3025718576
        },
        {
          "date": "2021-09-30",
          "equity": 770821.521335708
        },
        {
          "date": "2021-10-31",
          "equity": 770821.521335708
        },
        {
          "date": "2021-11-30",
          "equity": 965902.2405883799
        },
        {
          "date": "2021-12-31",
          "equity": 991007.9085276251
        },
        {
          "date": "2022-01-31",
          "equity": 991007.9085276251
        },
        {
          "date": "2022-02-28",
          "equity": 1222165.9714556409
        },
        {
          "date": "2022-03-31",
          "equity": 1222165.9714556409
        },
        {
          "date": "2022-04-30",
          "equity": 1222165.9714556409
        },
        {
          "date": "2022-05-31",
          "equity": 1222165.9714556409
        },
        {
          "date": "2022-06-30",
          "equity": 1222165.9714556409
        },
        {
          "date": "2022-07-31",
          "equity": 1219097.3551207646
        },
        {
          "date": "2022-08-31",
          "equity": 1219097.3551207646
        },
        {
          "date": "2022-09-30",
          "equity": 1219097.3551207646
        },
        {
          "date": "2022-10-31",
          "equity": 1288300.9672905002
        },
        {
          "date": "2022-11-30",
          "equity": 1288300.9672905002
        },
        {
          "date": "2022-12-31",
          "equity": 1288300.9672905002
        },
        {
          "date": "2023-01-31",
          "equity": 1288300.9672905002
        },
        {
          "date": "2023-02-28",
          "equity": 1250325.403459936
        },
        {
          "date": "2023-03-31",
          "equity": 1250325.403459936
        },
        {
          "date": "2023-04-30",
          "equity": 1250325.403459936
        },
        {
          "date": "2023-05-31",
          "equity": 1274027.5297736384
        },
        {
          "date": "2023-06-30",
          "equity": 1274027.5297736384
        },
        {
          "date": "2023-07-31",
          "equity": 1274027.5297736384
        },
        {
          "date": "2023-08-31",
          "equity": 1274027.5297736384
        },
        {
          "date": "2023-09-30",
          "equity": 1274027.5297736384
        },
        {
          "date": "2023-10-31",
          "equity": 1354481.7114602965
        },
        {
          "date": "2023-11-30",
          "equity": 1807401.1127000568
        },
        {
          "date": "2023-12-31",
          "equity": 1789308.5701806613
        },
        {
          "date": "2024-01-31",
          "equity": 1789308.5701806613
        },
        {
          "date": "2024-02-29",
          "equity": 1824270.6818489793
        },
        {
          "date": "2024-03-31",
          "equity": 1824270.6818489793
        },
        {
          "date": "2024-04-30",
          "equity": 1824270.6818489793
        },
        {
          "date": "2024-05-31",
          "equity": 1824270.6818489793
        },
        {
          "date": "2024-06-30",
          "equity": 1854537.4199498876
        },
        {
          "date": "2024-07-31",
          "equity": 1854537.4199498876
        },
        {
          "date": "2024-08-31",
          "equity": 1854537.4199498876
        },
        {
          "date": "2024-09-30",
          "equity": 1854537.4199498876
        },
        {
          "date": "2024-10-31",
          "equity": 1928171.2590263737
        },
        {
          "date": "2024-11-30",
          "equity": 1928171.2590263737
        },
        {
          "date": "2024-12-31",
          "equity": 1928171.2590263737
        },
        {
          "date": "2025-01-31",
          "equity": 1928171.2590263737
        },
        {
          "date": "2025-02-28",
          "equity": 1928171.2590263737
        },
        {
          "date": "2025-03-31",
          "equity": 1928171.2590263737
        },
        {
          "date": "2025-04-30",
          "equity": 1928171.2590263737
        },
        {
          "date": "2025-05-31",
          "equity": 1928171.2590263737
        },
        {
          "date": "2025-06-30",
          "equity": 2008690.4189124287
        },
        {
          "date": "2025-07-31",
          "equity": 1974508.8409802301
        },
        {
          "date": "2025-08-31",
          "equity": 1974508.8409802301
        },
        {
          "date": "2025-09-30",
          "equity": 2021673.0166127733
        },
        {
          "date": "2025-10-31",
          "equity": 2098358.119753525
        },
        {
          "date": "2025-11-30",
          "equity": 2098358.119753525
        },
        {
          "date": "2025-12-31",
          "equity": 2316235.8068667213
        },
        {
          "date": "2026-01-31",
          "equity": 2509961.8425172647
        },
        {
          "date": "2026-02-28",
          "equity": 2509961.8425172647
        },
        {
          "date": "2026-03-31",
          "equity": 2509961.8425172647
        },
        {
          "date": "2026-04-30",
          "equity": 2511043.517927504
        },
        {
          "date": "2026-05-31",
          "equity": 2801971.3573804037
        },
        {
          "date": "2026-06-30",
          "equity": 2801971.3573804037
        },
        {
          "date": "2026-07-31",
          "equity": 2801971.3573804037
        }
      ],
      "metrics": {
        "trades": 156,
        "total_return_pct": 2701.971357380404,
        "cagr_pct": 24.88008232822081,
        "sharpe": 1.1889046810128534,
        "max_dd_pct": -12.330891862590782,
        "win_rate_pct": 66.66666666666666,
        "payoff": 2.4401319905672327,
        "expectancy_pct": 2.307490082012022,
        "avg_win_pct": 4.353245341870741,
        "avg_loss_pct": -1.7840204377054154,
        "profit_factor": 4.880263981134463
      },
      "last_close": 162.29600524902344,
      "last_date": "2026-07-08T00:00:00"
    },
    "EURJPY": {
      "pair": "EURJPY",
      "current_equity": 4461694.779612825,
      "today_signal": null,
      "open_position": null,
      "yesterday_result": null,
      "recent_trades": [
        {
          "entry_date": "2024-09-11T00:00:00",
          "exit_date": "2024-09-12T00:00:00",
          "direction": 1,
          "entry_price": 156.73300170898438,
          "exit_price": 157.23561215910485,
          "stop_price": 157.23561215910485,
          "target_price": 161.12880172729493,
          "leverage": 6.2367585740175855,
          "pnl_pct": 0.019204155027210193,
          "reason": "stop",
          "hold_days": 1
        },
        {
          "entry_date": "2025-02-04T00:00:00",
          "exit_date": "2025-02-05T00:00:00",
          "direction": 1,
          "entry_price": 160.3509979248047,
          "exit_price": 158.90298590306557,
          "stop_price": 158.90298590306557,
          "target_price": 161.928214263916,
          "leverage": 2.214774401281794,
          "pnl_pct": -0.020276240800486994,
          "reason": "stop",
          "hold_days": 1
        },
        {
          "entry_date": "2025-02-06T00:00:00",
          "exit_date": "2025-02-07T00:00:00",
          "direction": 1,
          "entry_price": 158.71299743652344,
          "exit_price": 158.66602134401006,
          "stop_price": 158.66602134401006,
          "target_price": 161.56586380004882,
          "leverage": 20.0,
          "pnl_pct": -0.008439900146194683,
          "reason": "stop",
          "hold_days": 1
        },
        {
          "entry_date": "2025-02-07T00:00:00",
          "exit_date": "2025-02-10T00:00:00",
          "direction": 1,
          "entry_price": 157.01699829101562,
          "exit_price": 158.20541152865766,
          "stop_price": 158.20541152865766,
          "target_price": 161.34341354370116,
          "leverage": 2.642464646431525,
          "pnl_pct": 0.019663416741474836,
          "reason": "stop",
          "hold_days": 3
        },
        {
          "entry_date": "2025-04-28T00:00:00",
          "exit_date": "2025-04-30T00:00:00",
          "direction": -1,
          "entry_price": 163.1529998779297,
          "exit_price": 161.750399017334,
          "stop_price": 163.6699636085014,
          "target_price": 161.750399017334,
          "leverage": 6.311970849386146,
          "pnl_pct": 0.05348927898932716,
          "reason": "target",
          "hold_days": 2
        },
        {
          "entry_date": "2025-05-02T00:00:00",
          "exit_date": "2025-05-05T00:00:00",
          "direction": -1,
          "entry_price": 164.2969970703125,
          "exit_price": 163.76152607114685,
          "stop_price": 163.76152607114685,
          "target_price": 161.78588180541993,
          "leverage": 6.136541374838698,
          "pnl_pct": 0.01925299409188684,
          "reason": "stop",
          "hold_days": 3
        },
        {
          "entry_date": "2025-05-05T00:00:00",
          "exit_date": "2025-05-06T00:00:00",
          "direction": -1,
          "entry_price": 163.7469940185547,
          "exit_price": 161.9161819458008,
          "stop_price": 164.3171764365788,
          "target_price": 161.9161819458008,
          "leverage": 5.743670405902717,
          "pnl_pct": 0.063516938281929,
          "reason": "target",
          "hold_days": 1
        },
        {
          "entry_date": "2025-06-09T00:00:00",
          "exit_date": "2025-06-10T00:00:00",
          "direction": -1,
          "entry_price": 165.04400634765625,
          "exit_price": 165.15484221777808,
          "stop_price": 165.15484221777808,
          "target_price": 163.34214477539064,
          "leverage": 20.0,
          "pnl_pct": -0.015854664827541026,
          "reason": "stop",
          "hold_days": 1
        },
        {
          "entry_date": "2025-06-12T00:00:00",
          "exit_date": "2025-06-13T00:00:00",
          "direction": -1,
          "entry_price": 165.947998046875,
          "exit_price": 165.79150619454344,
          "stop_price": 165.79150619454344,
          "target_price": 163.4689453125,
          "leverage": 20.0,
          "pnl_pct": 0.01644995467712734,
          "reason": "stop",
          "hold_days": 1
        },
        {
          "entry_date": "2025-09-03T00:00:00",
          "exit_date": "2025-09-04T00:00:00",
          "direction": -1,
          "entry_price": 172.81700134277344,
          "exit_price": 173.02359985138148,
          "stop_price": 173.02359985138148,
          "target_price": 171.94364166259766,
          "leverage": 16.729743356535444,
          "pnl_pct": -0.021936122398438434,
          "reason": "stop",
          "hold_days": 1
        },
        {
          "entry_date": "2025-09-04T00:00:00",
          "exit_date": "2025-09-05T00:00:00",
          "direction": -1,
          "entry_price": 172.5469970703125,
          "exit_price": 173.0267774622497,
          "stop_price": 173.0267774622497,
          "target_price": 172.04204177856445,
          "leverage": 7.192749014757515,
          "pnl_pct": -0.02083371477184578,
          "reason": "stop",
          "hold_days": 1
        },
        {
          "entry_date": "2025-09-05T00:00:00",
          "exit_date": "2025-09-08T00:00:00",
          "direction": -1,
          "entry_price": 172.95399475097656,
          "exit_price": 173.08169955722076,
          "stop_price": 173.08169955722076,
          "target_price": 172.08664169311524,
          "leverage": 20.0,
          "pnl_pct": -0.017080242229370345,
          "reason": "stop",
          "hold_days": 3
        },
        {
          "entry_date": "2025-09-08T00:00:00",
          "exit_date": "2025-09-09T00:00:00",
          "direction": -1,
          "entry_price": 173.75599670410156,
          "exit_price": 173.1928069894708,
          "stop_price": 173.1928069894708,
          "target_price": 172.1618911743164,
          "leverage": 6.170425069570666,
          "pnl_pct": 0.019289759756599526,
          "reason": "stop",
          "hold_days": 1
        },
        {
          "entry_date": "2025-09-19T00:00:00",
          "exit_date": "2025-09-23T00:00:00",
          "direction": -1,
          "entry_price": 174.4320068359375,
          "exit_price": 174.44662016361298,
          "stop_price": 174.44662016361298,
          "target_price": 172.6276985168457,
          "leverage": 20.0,
          "pnl_pct": -0.003968689955855682,
          "reason": "stop",
          "hold_days": 4
        },
        {
          "entry_date": "2025-11-13T00:00:00",
          "exit_date": "2025-11-14T00:00:00",
          "direction": -1,
          "entry_price": 179.32400512695312,
          "exit_price": 179.2827251382218,
          "stop_price": 179.2827251382218,
          "target_price": 177.03015060424804,
          "leverage": 20.0,
          "pnl_pct": 0.0023733563965702637,
          "reason": "stop",
          "hold_days": 1
        },
        {
          "entry_date": "2025-11-14T00:00:00",
          "exit_date": "2025-11-17T00:00:00",
          "direction": -1,
          "entry_price": 179.83399963378906,
          "exit_price": 179.673209047564,
          "stop_price": 179.673209047564,
          "target_price": 177.2061004638672,
          "leverage": 20.0,
          "pnl_pct": 0.01565783850793125,
          "reason": "stop",
          "hold_days": 3
        },
        {
          "entry_date": "2025-11-20T00:00:00",
          "exit_date": "2025-11-21T00:00:00",
          "direction": -1,
          "entry_price": 181.16299438476562,
          "exit_price": 180.9206996155097,
          "stop_price": 180.9206996155097,
          "target_price": 178.01579895019532,
          "leverage": 14.95393358602923,
          "pnl_pct": 0.018349118302353834,
          "reason": "stop",
          "hold_days": 1
        },
        {
          "entry_date": "2025-12-22T00:00:00",
          "exit_date": "2025-12-23T00:00:00",
          "direction": -1,
          "entry_price": 184.56399536132812,
          "exit_price": 183.5197156300776,
          "stop_price": 183.5197156300776,
          "target_price": 181.49990005493163,
          "leverage": 3.534761612969592,
          "pnl_pct": 0.01961696086974608,
          "reason": "stop",
          "hold_days": 1
        },
        {
          "entry_date": "2026-01-14T00:00:00",
          "exit_date": "2026-01-16T00:00:00",
          "direction": -1,
          "entry_price": 185.33299255371094,
          "exit_price": 183.47074966430665,
          "stop_price": 185.41812106586374,
          "target_price": 183.47074966430665,
          "leverage": 20.0,
          "pnl_pct": 0.1988035550519036,
          "reason": "target",
          "hold_days": 2
        },
        {
          "entry_date": "2026-01-21T00:00:00",
          "exit_date": "2026-01-22T00:00:00",
          "direction": -1,
          "entry_price": 185.45399475097656,
          "exit_price": 185.402785473577,
          "stop_price": 185.402785473577,
          "target_price": 183.92644958496095,
          "leverage": 20.0,
          "pnl_pct": 0.003365716380653608,
          "reason": "stop",
          "hold_days": 1
        },
        {
          "entry_date": "2026-01-23T00:00:00",
          "exit_date": "2026-01-26T00:00:00",
          "direction": -1,
          "entry_price": 186.2760009765625,
          "exit_price": 183.99324951171874,
          "stop_price": 185.7240618637557,
          "target_price": 183.99324951171874,
          "leverage": 6.749875000859701,
          "pnl_pct": 0.08199279276791668,
          "reason": "target",
          "hold_days": 3
        },
        {
          "entry_date": "2026-01-27T00:00:00",
          "exit_date": "2026-02-02T00:00:00",
          "direction": 1,
          "entry_price": 183.27200317382812,
          "exit_price": 184.10414962768556,
          "stop_price": 181.96883122077614,
          "target_price": 184.10414962768556,
          "leverage": 2.812706377613653,
          "pnl_pct": 0.012464148755740371,
          "reason": "target",
          "hold_days": 6
        },
        {
          "entry_date": "2026-02-12T00:00:00",
          "exit_date": "2026-02-13T00:00:00",
          "direction": 1,
          "entry_price": 181.9709930419922,
          "exit_price": 181.8735254545406,
          "stop_price": 181.8735254545406,
          "target_price": 184.31489944458008,
          "leverage": 20.0,
          "pnl_pct": -0.012910583768091894,
          "reason": "stop",
          "hold_days": 1
        },
        {
          "entry_date": "2026-02-13T00:00:00",
          "exit_date": "2026-02-16T00:00:00",
          "direction": 1,
          "entry_price": 181.31300354003906,
          "exit_price": 181.45313442008117,
          "stop_price": 181.45313442008117,
          "target_price": 184.1922492980957,
          "leverage": 20.0,
          "pnl_pct": 0.013251215047637708,
          "reason": "stop",
          "hold_days": 3
        },
        {
          "entry_date": "2026-04-08T00:00:00",
          "exit_date": "2026-04-09T00:00:00",
          "direction": -1,
          "entry_price": 185.46200561523438,
          "exit_price": 184.9843473521288,
          "stop_price": 184.9843473521288,
          "target_price": 183.65519943237305,
          "leverage": 7.765468324966037,
          "pnl_pct": 0.019162581219888612,
          "reason": "stop",
          "hold_days": 1
        },
        {
          "entry_date": "2026-04-10T00:00:00",
          "exit_date": "2026-04-13T00:00:00",
          "direction": -1,
          "entry_price": 185.9980010986328,
          "exit_price": 185.6008320563523,
          "stop_price": 185.6008320563523,
          "target_price": 183.81779937744142,
          "leverage": 9.366188262339987,
          "pnl_pct": 0.018992872159161196,
          "reason": "stop",
          "hold_days": 3
        },
        {
          "entry_date": "2026-04-13T00:00:00",
          "exit_date": "2026-04-14T00:00:00",
          "direction": -1,
          "entry_price": 186.3990020751953,
          "exit_price": 186.06811517275128,
          "stop_price": 186.06811517275128,
          "target_price": 183.945849609375,
          "leverage": 11.26662921369164,
          "pnl_pct": 0.018791127732631686,
          "reason": "stop",
          "hold_days": 1
        },
        {
          "entry_date": "2026-04-14T00:00:00",
          "exit_date": "2026-04-15T00:00:00",
          "direction": -1,
          "entry_price": 187.3459930419922,
          "exit_price": 186.48628203583456,
          "stop_price": 186.48628203583456,
          "target_price": 184.14414978027344,
          "leverage": 4.358348135597629,
          "pnl_pct": 0.019534727371017673,
          "reason": "stop",
          "hold_days": 1
        },
        {
          "entry_date": "2026-06-24T00:00:00",
          "exit_date": "2026-06-25T00:00:00",
          "direction": 1,
          "entry_price": 183.8509979248047,
          "exit_price": 184.20531588510482,
          "stop_price": 184.20531588510482,
          "target_price": 185.33714904785157,
          "leverage": 10.377740816134065,
          "pnl_pct": 0.01887107049368548,
          "reason": "stop",
          "hold_days": 1
        },
        {
          "entry_date": "2026-06-26T00:00:00",
          "exit_date": "2026-06-30T00:00:00",
          "direction": 1,
          "entry_price": 183.8520050048828,
          "exit_price": 185.18099975585938,
          "stop_price": 183.55060915892025,
          "target_price": 185.18099975585938,
          "leverage": 12.200035764774366,
          "pnl_pct": 0.08686216273459647,
          "reason": "target",
          "hold_days": 4
        }
      ],
      "equity_curve": [
        {
          "date": "2011-07-31",
          "equity": 100000.0
        },
        {
          "date": "2011-08-31",
          "equity": 100000.0
        },
        {
          "date": "2011-09-30",
          "equity": 101639.3018127812
        },
        {
          "date": "2011-10-31",
          "equity": 101639.3018127812
        },
        {
          "date": "2011-11-30",
          "equity": 101639.3018127812
        },
        {
          "date": "2011-12-31",
          "equity": 101256.8626720103
        },
        {
          "date": "2012-01-31",
          "equity": 101256.8626720103
        },
        {
          "date": "2012-02-29",
          "equity": 101256.8626720103
        },
        {
          "date": "2012-03-31",
          "equity": 101256.8626720103
        },
        {
          "date": "2012-04-30",
          "equity": 101256.8626720103
        },
        {
          "date": "2012-05-31",
          "equity": 102597.56282827463
        },
        {
          "date": "2012-06-30",
          "equity": 102597.56282827463
        },
        {
          "date": "2012-07-31",
          "equity": 104484.0147847573
        },
        {
          "date": "2012-08-31",
          "equity": 104484.0147847573
        },
        {
          "date": "2012-09-30",
          "equity": 102943.78236575439
        },
        {
          "date": "2012-10-31",
          "equity": 100680.52834750603
        },
        {
          "date": "2012-11-30",
          "equity": 102274.21748185827
        },
        {
          "date": "2012-12-31",
          "equity": 102274.21748185827
        },
        {
          "date": "2013-01-31",
          "equity": 102274.21748185827
        },
        {
          "date": "2013-02-28",
          "equity": 102274.21748185827
        },
        {
          "date": "2013-03-31",
          "equity": 102274.21748185827
        },
        {
          "date": "2013-04-30",
          "equity": 102274.21748185827
        },
        {
          "date": "2013-05-31",
          "equity": 104225.9720132194
        },
        {
          "date": "2013-06-30",
          "equity": 105934.62915524858
        },
        {
          "date": "2013-07-31",
          "equity": 105934.62915524858
        },
        {
          "date": "2013-08-31",
          "equity": 138869.92584095037
        },
        {
          "date": "2013-09-30",
          "equity": 171475.18254272602
        },
        {
          "date": "2013-10-31",
          "equity": 174629.649492699
        },
        {
          "date": "2013-11-30",
          "equity": 174629.649492699
        },
        {
          "date": "2013-12-31",
          "equity": 174629.649492699
        },
        {
          "date": "2014-01-31",
          "equity": 174629.649492699
        },
        {
          "date": "2014-02-28",
          "equity": 174629.649492699
        },
        {
          "date": "2014-03-31",
          "equity": 174629.649492699
        },
        {
          "date": "2014-04-30",
          "equity": 174629.649492699
        },
        {
          "date": "2014-05-31",
          "equity": 184136.9738857391
        },
        {
          "date": "2014-06-30",
          "equity": 184136.9738857391
        },
        {
          "date": "2014-07-31",
          "equity": 185680.94799560786
        },
        {
          "date": "2014-08-31",
          "equity": 186638.1696465626
        },
        {
          "date": "2014-09-30",
          "equity": 220679.71465212284
        },
        {
          "date": "2014-10-31",
          "equity": 220679.71465212284
        },
        {
          "date": "2014-11-30",
          "equity": 220679.71465212284
        },
        {
          "date": "2014-12-31",
          "equity": 220679.71465212284
        },
        {
          "date": "2015-01-31",
          "equity": 220679.71465212284
        },
        {
          "date": "2015-02-28",
          "equity": 220679.71465212284
        },
        {
          "date": "2015-03-31",
          "equity": 220679.71465212284
        },
        {
          "date": "2015-04-30",
          "equity": 220050.9813692074
        },
        {
          "date": "2015-05-31",
          "equity": 220050.9813692074
        },
        {
          "date": "2015-06-30",
          "equity": 215495.672914704
        },
        {
          "date": "2015-07-31",
          "equity": 215495.672914704
        },
        {
          "date": "2015-08-31",
          "equity": 215495.672914704
        },
        {
          "date": "2015-09-30",
          "equity": 215495.672914704
        },
        {
          "date": "2015-10-31",
          "equity": 215495.672914704
        },
        {
          "date": "2015-11-30",
          "equity": 215495.672914704
        },
        {
          "date": "2015-12-31",
          "equity": 215495.672914704
        },
        {
          "date": "2016-01-31",
          "equity": 215495.672914704
        },
        {
          "date": "2016-02-29",
          "equity": 215495.672914704
        },
        {
          "date": "2016-03-31",
          "equity": 215495.672914704
        },
        {
          "date": "2016-04-30",
          "equity": 261951.08874782035
        },
        {
          "date": "2016-05-31",
          "equity": 261951.08874782035
        },
        {
          "date": "2016-06-30",
          "equity": 265738.15330530383
        },
        {
          "date": "2016-07-31",
          "equity": 265738.15330530383
        },
        {
          "date": "2016-08-31",
          "equity": 265738.15330530383
        },
        {
          "date": "2016-09-30",
          "equity": 270696.3085302924
        },
        {
          "date": "2016-10-31",
          "equity": 270696.3085302924
        },
        {
          "date": "2016-11-30",
          "equity": 262248.33518466074
        },
        {
          "date": "2016-12-31",
          "equity": 262248.33518466074
        },
        {
          "date": "2017-01-31",
          "equity": 296420.6493517329
        },
        {
          "date": "2017-02-28",
          "equity": 307360.09528717515
        },
        {
          "date": "2017-03-31",
          "equity": 307360.09528717515
        },
        {
          "date": "2017-04-30",
          "equity": 307360.09528717515
        },
        {
          "date": "2017-05-31",
          "equity": 307360.09528717515
        },
        {
          "date": "2017-06-30",
          "equity": 300851.42423294875
        },
        {
          "date": "2017-07-31",
          "equity": 300851.42423294875
        },
        {
          "date": "2017-08-31",
          "equity": 463624.80017313216
        },
        {
          "date": "2017-09-30",
          "equity": 472171.76693207055
        },
        {
          "date": "2017-10-31",
          "equity": 566287.9572837082
        },
        {
          "date": "2017-11-30",
          "equity": 566287.9572837082
        },
        {
          "date": "2017-12-31",
          "equity": 603721.76453728
        },
        {
          "date": "2018-01-31",
          "equity": 603721.76453728
        },
        {
          "date": "2018-02-28",
          "equity": 653904.9323867465
        },
        {
          "date": "2018-03-31",
          "equity": 709117.4627298554
        },
        {
          "date": "2018-04-30",
          "equity": 704300.8546353437
        },
        {
          "date": "2018-05-31",
          "equity": 704300.8546353437
        },
        {
          "date": "2018-06-30",
          "equity": 704300.8546353437
        },
        {
          "date": "2018-07-31",
          "equity": 704300.8546353437
        },
        {
          "date": "2018-08-31",
          "equity": 718170.9805912431
        },
        {
          "date": "2018-09-30",
          "equity": 718170.9805912431
        },
        {
          "date": "2018-10-31",
          "equity": 718170.9805912431
        },
        {
          "date": "2018-11-30",
          "equity": 718170.9805912431
        },
        {
          "date": "2018-12-31",
          "equity": 718170.9805912431
        },
        {
          "date": "2019-01-31",
          "equity": 718170.9805912431
        },
        {
          "date": "2019-02-28",
          "equity": 746936.2118236576
        },
        {
          "date": "2019-03-31",
          "equity": 762374.4591610945
        },
        {
          "date": "2019-04-30",
          "equity": 762374.4591610945
        },
        {
          "date": "2019-05-31",
          "equity": 762374.4591610945
        },
        {
          "date": "2019-06-30",
          "equity": 762374.4591610945
        },
        {
          "date": "2019-07-31",
          "equity": 762374.4591610945
        },
        {
          "date": "2019-08-31",
          "equity": 762374.4591610945
        },
        {
          "date": "2019-09-30",
          "equity": 995408.4297736428
        },
        {
          "date": "2019-10-31",
          "equity": 995408.4297736428
        },
        {
          "date": "2019-11-30",
          "equity": 995408.4297736428
        },
        {
          "date": "2019-12-31",
          "equity": 1017139.3082198289
        },
        {
          "date": "2020-01-31",
          "equity": 1017139.3082198289
        },
        {
          "date": "2020-02-29",
          "equity": 1017139.3082198289
        },
        {
          "date": "2020-03-31",
          "equity": 1459628.9509059044
        },
        {
          "date": "2020-04-30",
          "equity": 1459628.9509059044
        },
        {
          "date": "2020-05-31",
          "equity": 1495329.556188142
        },
        {
          "date": "2020-06-30",
          "equity": 1495329.556188142
        },
        {
          "date": "2020-07-31",
          "equity": 1495329.556188142
        },
        {
          "date": "2020-08-31",
          "equity": 1495329.556188142
        },
        {
          "date": "2020-09-30",
          "equity": 1550219.829284534
        },
        {
          "date": "2020-10-31",
          "equity": 1578860.6165782113
        },
        {
          "date": "2020-11-30",
          "equity": 1609026.2541820377
        },
        {
          "date": "2020-12-31",
          "equity": 1609026.2541820377
        },
        {
          "date": "2021-01-31",
          "equity": 1665359.494873798
        },
        {
          "date": "2021-02-28",
          "equity": 1665359.494873798
        },
        {
          "date": "2021-03-31",
          "equity": 1665359.494873798
        },
        {
          "date": "2021-04-30",
          "equity": 1697414.5863161855
        },
        {
          "date": "2021-05-31",
          "equity": 1662102.9738465783
        },
        {
          "date": "2021-06-30",
          "equity": 1662102.9738465783
        },
        {
          "date": "2021-07-31",
          "equity": 1662102.9738465783
        },
        {
          "date": "2021-08-31",
          "equity": 1692631.2330939192
        },
        {
          "date": "2021-09-30",
          "equity": 1692631.2330939192
        },
        {
          "date": "2021-10-31",
          "equity": 1766250.128725294
        },
        {
          "date": "2021-11-30",
          "equity": 1766250.128725294
        },
        {
          "date": "2021-12-31",
          "equity": 1766250.128725294
        },
        {
          "date": "2022-01-31",
          "equity": 1766250.128725294
        },
        {
          "date": "2022-02-28",
          "equity": 1766250.128725294
        },
        {
          "date": "2022-03-31",
          "equity": 1766250.128725294
        },
        {
          "date": "2022-04-30",
          "equity": 1766250.128725294
        },
        {
          "date": "2022-05-31",
          "equity": 1800982.4017653624
        },
        {
          "date": "2022-06-30",
          "equity": 1800982.4017653624
        },
        {
          "date": "2022-07-31",
          "equity": 1745267.4029709597
        },
        {
          "date": "2022-08-31",
          "equity": 2016246.306992643
        },
        {
          "date": "2022-09-30",
          "equity": 2088278.8806151226
        },
        {
          "date": "2022-10-31",
          "equity": 2088278.8806151226
        },
        {
          "date": "2022-11-30",
          "equity": 2088278.8806151226
        },
        {
          "date": "2022-12-31",
          "equity": 2129342.0849321894
        },
        {
          "date": "2023-01-31",
          "equity": 2386814.170934813
        },
        {
          "date": "2023-02-28",
          "equity": 2337897.0222670767
        },
        {
          "date": "2023-03-31",
          "equity": 2290376.668616415
        },
        {
          "date": "2023-04-30",
          "equity": 2290376.668616415
        },
        {
          "date": "2023-05-31",
          "equity": 2290376.668616415
        },
        {
          "date": "2023-06-30",
          "equity": 2357450.60503749
        },
        {
          "date": "2023-07-31",
          "equity": 2357450.60503749
        },
        {
          "date": "2023-08-31",
          "equity": 2383393.5613255473
        },
        {
          "date": "2023-09-30",
          "equity": 2414077.29654342
        },
        {
          "date": "2023-10-31",
          "equity": 2460116.74261335
        },
        {
          "date": "2023-11-30",
          "equity": 2460116.74261335
        },
        {
          "date": "2023-12-31",
          "equity": 2460116.74261335
        },
        {
          "date": "2024-01-31",
          "equity": 2460116.74261335
        },
        {
          "date": "2024-02-29",
          "equity": 2460116.74261335
        },
        {
          "date": "2024-03-31",
          "equity": 2460116.74261335
        },
        {
          "date": "2024-04-30",
          "equity": 2492183.012714061
        },
        {
          "date": "2024-05-31",
          "equity": 2492183.012714061
        },
        {
          "date": "2024-06-30",
          "equity": 2492183.012714061
        },
        {
          "date": "2024-07-31",
          "equity": 2492183.012714061
        },
        {
          "date": "2024-08-31",
          "equity": 2492183.012714061
        },
        {
          "date": "2024-09-30",
          "equity": 2479220.0511761615
        },
        {
          "date": "2024-10-31",
          "equity": 2479220.0511761615
        },
        {
          "date": "2024-11-30",
          "equity": 2479220.0511761615
        },
        {
          "date": "2024-12-31",
          "equity": 2479220.0511761615
        },
        {
          "date": "2025-01-31",
          "equity": 2479220.0511761615
        },
        {
          "date": "2025-02-28",
          "equity": 2455809.0558529655
        },
        {
          "date": "2025-03-31",
          "equity": 2455809.0558529655
        },
        {
          "date": "2025-04-30",
          "equity": 2587168.5115860007
        },
        {
          "date": "2025-05-31",
          "equity": 2804472.1000323338
        },
        {
          "date": "2025-06-30",
          "equity": 2805410.1435952145
        },
        {
          "date": "2025-07-31",
          "equity": 2805410.1435952145
        },
        {
          "date": "2025-08-31",
          "equity": 2805410.1435952145
        },
        {
          "date": "2025-09-30",
          "equity": 2681073.688443699
        },
        {
          "date": "2025-10-31",
          "equity": 2681073.688443699
        },
        {
          "date": "2025-11-30",
          "equity": 2779600.500943569
        },
        {
          "date": "2025-12-31",
          "equity": 2834127.8152041053
        },
        {
          "date": "2026-01-31",
          "equity": 3688510.976694209
        },
        {
          "date": "2026-02-28",
          "equity": 3735118.30948367
        },
        {
          "date": "2026-03-31",
          "equity": 3735118.30948367
        },
        {
          "date": "2026-04-30",
          "equity": 4029082.464284046
        },
        {
          "date": "2026-05-31",
          "equity": 4029082.464284046
        },
        {
          "date": "2026-06-30",
          "equity": 4461694.779612825
        },
        {
          "date": "2026-07-31",
          "equity": 4461694.779612825
        }
      ],
      "metrics": {
        "trades": 165,
        "total_return_pct": 4361.694779612825,
        "cagr_pct": 28.813576783373573,
        "sharpe": 1.1934506823911657,
        "max_dd_pct": -5.86703551605941,
        "win_rate_pct": 70.3030303030303,
        "payoff": 2.5759317020783383,
        "expectancy_pct": 2.505321157726766,
        "avg_win_pct": 4.26260624928615,
        "avg_loss_pct": -1.6547823243321835,
        "profit_factor": 6.098124029409944
      },
      "last_close": 185.08999633789062,
      "last_date": "2026-07-08T00:00:00"
    },
    "GBPJPY": {
      "pair": "GBPJPY",
      "current_equity": 6422138.990694628,
      "today_signal": null,
      "open_position": null,
      "yesterday_result": {
        "entry_date": "2026-07-07T00:00:00",
        "exit_date": "2026-07-08T00:00:00",
        "direction": -1,
        "entry_price": 217.11000061035156,
        "exit_price": 216.66443433233934,
        "stop_price": 216.66443433233934,
        "target_price": 214.32234878540038,
        "leverage": 9.745351536877122,
        "pnl_pct": 0.019102265993323157,
        "reason": "stop",
        "hold_days": 1
      },
      "recent_trades": [
        {
          "entry_date": "2024-03-21T00:00:00",
          "exit_date": "2024-04-09T00:00:00",
          "direction": -1,
          "entry_price": 192.93600463867188,
          "exit_price": 192.34500344758638,
          "stop_price": 192.34500344758638,
          "target_price": 189.9717987060547,
          "leverage": 6.529124054193695,
          "pnl_pct": 0.019323182413109326,
          "reason": "stop",
          "hold_days": 19
        },
        {
          "entry_date": "2024-04-26T00:00:00",
          "exit_date": "2024-04-29T00:00:00",
          "direction": -1,
          "entry_price": 194.61700439453125,
          "exit_price": 193.60991322316602,
          "stop_price": 193.60991322316602,
          "target_price": 191.73604888916014,
          "leverage": 3.8649331843651193,
          "pnl_pct": 0.019602816496288263,
          "reason": "stop",
          "hold_days": 3
        },
        {
          "entry_date": "2024-05-01T00:00:00",
          "exit_date": "2024-05-02T00:00:00",
          "direction": -1,
          "entry_price": 196.98199462890625,
          "exit_price": 192.54709854125977,
          "stop_price": 196.9675088927535,
          "target_price": 192.54709854125977,
          "leverage": 20.0,
          "pnl_pct": 0.4482537701949549,
          "reason": "target",
          "hold_days": 1
        },
        {
          "entry_date": "2024-06-25T00:00:00",
          "exit_date": "2024-06-26T00:00:00",
          "direction": -1,
          "entry_price": 202.51300048828125,
          "exit_price": 202.13526248634153,
          "stop_price": 202.13526248634153,
          "target_price": 200.17499847412108,
          "leverage": 10.722405447604363,
          "pnl_pct": 0.018941064976396433,
          "reason": "stop",
          "hold_days": 1
        },
        {
          "entry_date": "2024-06-27T00:00:00",
          "exit_date": "2024-06-28T00:00:00",
          "direction": -1,
          "entry_price": 202.71600341796875,
          "exit_price": 203.01954924758329,
          "stop_price": 203.01954924758329,
          "target_price": 200.3806480407715,
          "leverage": 13.356533586733347,
          "pnl_pct": -0.02131775818006773,
          "reason": "stop",
          "hold_days": 1
        },
        {
          "entry_date": "2024-09-11T00:00:00",
          "exit_date": "2024-09-12T00:00:00",
          "direction": 1,
          "entry_price": 186.02499389648438,
          "exit_price": 186.3821506601274,
          "stop_price": 186.3821506601274,
          "target_price": 190.14865112304688,
          "leverage": 10.416994039201112,
          "pnl_pct": 0.01888004360908645,
          "reason": "stop",
          "hold_days": 1
        },
        {
          "entry_date": "2025-02-07T00:00:00",
          "exit_date": "2025-02-10T00:00:00",
          "direction": 1,
          "entry_price": 188.01300048828125,
          "exit_price": 189.33428805233575,
          "stop_price": 189.33428805233575,
          "target_price": 192.2739044189453,
          "leverage": 2.845905851279564,
          "pnl_pct": 0.01969726499296447,
          "reason": "stop",
          "hold_days": 3
        },
        {
          "entry_date": "2025-02-11T00:00:00",
          "exit_date": "2025-02-12T00:00:00",
          "direction": 1,
          "entry_price": 187.55099487304688,
          "exit_price": 191.72865371704103,
          "stop_price": 187.68601292408158,
          "target_price": 191.72865371704103,
          "leverage": 20.0,
          "pnl_pct": 0.44336302740579636,
          "reason": "target",
          "hold_days": 1
        },
        {
          "entry_date": "2025-03-19T00:00:00",
          "exit_date": "2025-03-24T00:00:00",
          "direction": -1,
          "entry_price": 194.27699279785156,
          "exit_price": 194.20135001584447,
          "stop_price": 194.20135001584447,
          "target_price": 190.5964500427246,
          "leverage": 20.0,
          "pnl_pct": 0.005728190580445229,
          "reason": "stop",
          "hold_days": 5
        },
        {
          "entry_date": "2025-06-24T00:00:00",
          "exit_date": "2025-06-25T00:00:00",
          "direction": -1,
          "entry_price": 197.64500427246094,
          "exit_price": 197.6433444912573,
          "stop_price": 197.6433444912573,
          "target_price": 195.0420265197754,
          "leverage": 20.0,
          "pnl_pct": -0.0018558747653520283,
          "reason": "stop",
          "hold_days": 1
        },
        {
          "entry_date": "2025-06-26T00:00:00",
          "exit_date": "2025-06-27T00:00:00",
          "direction": -1,
          "entry_price": 198.3719940185547,
          "exit_price": 198.38963095133522,
          "stop_price": 198.38963095133522,
          "target_price": 195.37552719116212,
          "leverage": 20.0,
          "pnl_pct": -0.0037945812831838427,
          "reason": "stop",
          "hold_days": 1
        },
        {
          "entry_date": "2025-08-01T00:00:00",
          "exit_date": "2025-08-04T00:00:00",
          "direction": 1,
          "entry_price": 199.14700317382812,
          "exit_price": 197.24895839011742,
          "stop_price": 197.24895839011742,
          "target_price": 198.57005081176757,
          "leverage": 2.098443670907418,
          "pnl_pct": -0.02021074318342373,
          "reason": "stop",
          "hold_days": 3
        },
        {
          "entry_date": "2025-08-04T00:00:00",
          "exit_date": "2025-08-05T00:00:00",
          "direction": 1,
          "entry_price": 195.79600524902344,
          "exit_price": 197.37619001540156,
          "stop_price": 197.37619001540156,
          "target_price": 198.64075088500977,
          "leverage": 2.4781406505746704,
          "pnl_pct": 0.01974686504482838,
          "reason": "stop",
          "hold_days": 1
        },
        {
          "entry_date": "2025-09-15T00:00:00",
          "exit_date": "2025-09-16T00:00:00",
          "direction": -1,
          "entry_price": 200.12600708007812,
          "exit_price": 200.396614402589,
          "stop_price": 200.396614402589,
          "target_price": 199.16490020751954,
          "leverage": 14.790878918070636,
          "pnl_pct": -0.021478156600821224,
          "reason": "stop",
          "hold_days": 1
        },
        {
          "entry_date": "2025-09-16T00:00:00",
          "exit_date": "2025-09-18T00:00:00",
          "direction": -1,
          "entry_price": 200.5,
          "exit_price": 200.50725912065226,
          "stop_price": 200.50725912065226,
          "target_price": 199.18990020751954,
          "leverage": 20.0,
          "pnl_pct": -0.002719114279527634,
          "reason": "stop",
          "hold_days": 2
        },
        {
          "entry_date": "2025-09-19T00:00:00",
          "exit_date": "2025-09-23T00:00:00",
          "direction": -1,
          "entry_price": 200.54800415039062,
          "exit_price": 199.35055084228514,
          "stop_price": 200.85036026453784,
          "target_price": 199.35055084228514,
          "leverage": 13.265682072679686,
          "pnl_pct": 0.07788519914184265,
          "reason": "target",
          "hold_days": 4
        },
        {
          "entry_date": "2025-10-01T00:00:00",
          "exit_date": "2025-10-02T00:00:00",
          "direction": 1,
          "entry_price": 198.94900512695312,
          "exit_price": 198.59629938591755,
          "stop_price": 198.59629938591755,
          "target_price": 199.7703010559082,
          "leverage": 11.28130234244669,
          "pnl_pct": -0.02113408984732021,
          "reason": "stop",
          "hold_days": 1
        },
        {
          "entry_date": "2025-10-02T00:00:00",
          "exit_date": "2025-10-03T00:00:00",
          "direction": 1,
          "entry_price": 198.25999450683594,
          "exit_price": 198.64158418260212,
          "stop_price": 198.64158418260212,
          "target_price": 199.7780014038086,
          "leverage": 10.39126617399999,
          "pnl_pct": 0.01895175361021795,
          "reason": "stop",
          "hold_days": 1
        },
        {
          "entry_date": "2025-10-07T00:00:00",
          "exit_date": "2025-10-08T00:00:00",
          "direction": -1,
          "entry_price": 202.7050018310547,
          "exit_price": 201.50844110040933,
          "stop_price": 201.50844110040933,
          "target_price": 199.70600128173828,
          "leverage": 3.3881272657464994,
          "pnl_pct": 0.019665708568102295,
          "reason": "stop",
          "hold_days": 1
        },
        {
          "entry_date": "2025-11-05T00:00:00",
          "exit_date": "2025-11-06T00:00:00",
          "direction": 1,
          "entry_price": 199.9199981689453,
          "exit_price": 200.7602097161101,
          "stop_price": 200.7602097161101,
          "target_price": 202.82720031738282,
          "leverage": 4.758801490971094,
          "pnl_pct": 0.01952392941831166,
          "reason": "stop",
          "hold_days": 1
        },
        {
          "entry_date": "2025-11-21T00:00:00",
          "exit_date": "2025-11-25T00:00:00",
          "direction": -1,
          "entry_price": 205.90499877929688,
          "exit_price": 205.9079752517268,
          "stop_price": 205.9079752517268,
          "target_price": 202.74900131225587,
          "leverage": 20.0,
          "pnl_pct": -0.0022317546991234773,
          "reason": "stop",
          "hold_days": 4
        },
        {
          "entry_date": "2026-02-05T00:00:00",
          "exit_date": "2026-02-06T00:00:00",
          "direction": -1,
          "entry_price": 214.1020050048828,
          "exit_price": 212.13319778442383,
          "stop_price": 214.4526430633277,
          "target_price": 212.13319778442383,
          "leverage": 12.21213726510107,
          "pnl_pct": 0.11115776930217182,
          "reason": "target",
          "hold_days": 1
        },
        {
          "entry_date": "2026-02-12T00:00:00",
          "exit_date": "2026-02-13T00:00:00",
          "direction": 1,
          "entry_price": 208.75900268554688,
          "exit_price": 209.7444681576099,
          "stop_price": 209.7444681576099,
          "target_price": 212.3505485534668,
          "leverage": 4.23675935085822,
          "pnl_pct": 0.01959410044152778,
          "reason": "stop",
          "hold_days": 1
        },
        {
          "entry_date": "2026-02-16T00:00:00",
          "exit_date": "2026-02-17T00:00:00",
          "direction": 1,
          "entry_price": 208.50599670410156,
          "exit_price": 208.03956378447455,
          "stop_price": 208.03956378447455,
          "target_price": 211.93989944458008,
          "leverage": 8.940449437867136,
          "pnl_pct": -0.02085757240359421,
          "reason": "stop",
          "hold_days": 1
        },
        {
          "entry_date": "2026-04-13T00:00:00",
          "exit_date": "2026-04-14T00:00:00",
          "direction": -1,
          "entry_price": 213.8260040283203,
          "exit_price": 214.2933036586255,
          "stop_price": 214.2933036586255,
          "target_price": 211.93379974365234,
          "leverage": 9.151558878344407,
          "pnl_pct": -0.020855981845606796,
          "reason": "stop",
          "hold_days": 1
        },
        {
          "entry_date": "2026-04-14T00:00:00",
          "exit_date": "2026-04-15T00:00:00",
          "direction": -1,
          "entry_price": 215.18699645996094,
          "exit_price": 214.61594855096433,
          "stop_price": 214.61594855096433,
          "target_price": 212.05869979858397,
          "leverage": 7.536565428917122,
          "pnl_pct": 0.01929953337767606,
          "reason": "stop",
          "hold_days": 1
        },
        {
          "entry_date": "2026-04-15T00:00:00",
          "exit_date": "2026-04-16T00:00:00",
          "direction": -1,
          "entry_price": 215.50100708007812,
          "exit_price": 215.29307889851324,
          "stop_price": 215.29307889851324,
          "target_price": 212.22689971923828,
          "leverage": 20.0,
          "pnl_pct": 0.017441049033710448,
          "reason": "stop",
          "hold_days": 1
        },
        {
          "entry_date": "2026-06-19T00:00:00",
          "exit_date": "2026-06-22T00:00:00",
          "direction": 1,
          "entry_price": 212.91600036621094,
          "exit_price": 214.44134826660155,
          "stop_price": 213.12647058936332,
          "target_price": 214.44134826660155,
          "leverage": 20.0,
          "pnl_pct": 0.14140298500830822,
          "reason": "target",
          "hold_days": 3
        },
        {
          "entry_date": "2026-06-22T00:00:00",
          "exit_date": "2026-06-24T00:00:00",
          "direction": 1,
          "entry_price": 213.24099731445312,
          "exit_price": 212.92264261853558,
          "stop_price": 212.92264261853558,
          "target_price": 214.40859832763672,
          "leverage": 13.396441142472156,
          "pnl_pct": -0.02125646018459736,
          "reason": "stop",
          "hold_days": 2
        },
        {
          "entry_date": "2026-07-07T00:00:00",
          "exit_date": "2026-07-08T00:00:00",
          "direction": -1,
          "entry_price": 217.11000061035156,
          "exit_price": 216.66443433233934,
          "stop_price": 216.66443433233934,
          "target_price": 214.32234878540038,
          "leverage": 9.745351536877122,
          "pnl_pct": 0.019102265993323157,
          "reason": "stop",
          "hold_days": 1
        }
      ],
      "equity_curve": [
        {
          "date": "2011-07-31",
          "equity": 100000.0
        },
        {
          "date": "2011-08-31",
          "equity": 100000.0
        },
        {
          "date": "2011-09-30",
          "equity": 95666.26989481869
        },
        {
          "date": "2011-10-31",
          "equity": 95666.26989481869
        },
        {
          "date": "2011-11-30",
          "equity": 95666.26989481869
        },
        {
          "date": "2011-12-31",
          "equity": 95666.26989481869
        },
        {
          "date": "2012-01-31",
          "equity": 96577.31935486126
        },
        {
          "date": "2012-02-29",
          "equity": 96577.31935486126
        },
        {
          "date": "2012-03-31",
          "equity": 96577.31935486126
        },
        {
          "date": "2012-04-30",
          "equity": 98468.65404611565
        },
        {
          "date": "2012-05-31",
          "equity": 98468.65404611565
        },
        {
          "date": "2012-06-30",
          "equity": 98468.65404611565
        },
        {
          "date": "2012-07-31",
          "equity": 98679.3840738236
        },
        {
          "date": "2012-08-31",
          "equity": 98068.65096474798
        },
        {
          "date": "2012-09-30",
          "equity": 99998.90542645151
        },
        {
          "date": "2012-10-31",
          "equity": 98624.68949550214
        },
        {
          "date": "2012-11-30",
          "equity": 100549.45261081615
        },
        {
          "date": "2012-12-31",
          "equity": 100549.45261081615
        },
        {
          "date": "2013-01-31",
          "equity": 100549.45261081615
        },
        {
          "date": "2013-02-28",
          "equity": 96450.23326444298
        },
        {
          "date": "2013-03-31",
          "equity": 96450.23326444298
        },
        {
          "date": "2013-04-30",
          "equity": 96450.23326444298
        },
        {
          "date": "2013-05-31",
          "equity": 95451.39710174689
        },
        {
          "date": "2013-06-30",
          "equity": 95451.39710174689
        },
        {
          "date": "2013-07-31",
          "equity": 96127.42508534156
        },
        {
          "date": "2013-08-31",
          "equity": 96127.42508534156
        },
        {
          "date": "2013-09-30",
          "equity": 96127.42508534156
        },
        {
          "date": "2013-10-31",
          "equity": 124742.19091548343
        },
        {
          "date": "2013-11-30",
          "equity": 127068.73957429451
        },
        {
          "date": "2013-12-31",
          "equity": 127068.73957429451
        },
        {
          "date": "2014-01-31",
          "equity": 129498.12696657608
        },
        {
          "date": "2014-02-28",
          "equity": 129498.12696657608
        },
        {
          "date": "2014-03-31",
          "equity": 129498.12696657608
        },
        {
          "date": "2014-04-30",
          "equity": 129498.12696657608
        },
        {
          "date": "2014-05-31",
          "equity": 130291.46075027056
        },
        {
          "date": "2014-06-30",
          "equity": 131081.1353191572
        },
        {
          "date": "2014-07-31",
          "equity": 131081.1353191572
        },
        {
          "date": "2014-08-31",
          "equity": 129228.27026958075
        },
        {
          "date": "2014-09-30",
          "equity": 145390.4279912596
        },
        {
          "date": "2014-10-31",
          "equity": 145390.4279912596
        },
        {
          "date": "2014-11-30",
          "equity": 145390.4279912596
        },
        {
          "date": "2014-12-31",
          "equity": 145390.4279912596
        },
        {
          "date": "2015-01-31",
          "equity": 145390.4279912596
        },
        {
          "date": "2015-02-28",
          "equity": 147905.32347409334
        },
        {
          "date": "2015-03-31",
          "equity": 153011.17191908442
        },
        {
          "date": "2015-04-30",
          "equity": 162432.44877229282
        },
        {
          "date": "2015-05-31",
          "equity": 162432.44877229282
        },
        {
          "date": "2015-06-30",
          "equity": 165648.85099101398
        },
        {
          "date": "2015-07-31",
          "equity": 165648.85099101398
        },
        {
          "date": "2015-08-31",
          "equity": 168873.78944463973
        },
        {
          "date": "2015-09-30",
          "equity": 168873.78944463973
        },
        {
          "date": "2015-10-31",
          "equity": 168873.78944463973
        },
        {
          "date": "2015-11-30",
          "equity": 169409.83109284492
        },
        {
          "date": "2015-12-31",
          "equity": 169409.83109284492
        },
        {
          "date": "2016-01-31",
          "equity": 169409.83109284492
        },
        {
          "date": "2016-02-29",
          "equity": 167972.94734111175
        },
        {
          "date": "2016-03-31",
          "equity": 167972.94734111175
        },
        {
          "date": "2016-04-30",
          "equity": 171281.78365898255
        },
        {
          "date": "2016-05-31",
          "equity": 171281.78365898255
        },
        {
          "date": "2016-06-30",
          "equity": 171281.78365898255
        },
        {
          "date": "2016-07-31",
          "equity": 171281.78365898255
        },
        {
          "date": "2016-08-31",
          "equity": 171281.78365898255
        },
        {
          "date": "2016-09-30",
          "equity": 171281.78365898255
        },
        {
          "date": "2016-10-31",
          "equity": 171281.78365898255
        },
        {
          "date": "2016-11-30",
          "equity": 171281.78365898255
        },
        {
          "date": "2016-12-31",
          "equity": 171281.78365898255
        },
        {
          "date": "2017-01-31",
          "equity": 173864.5715530214
        },
        {
          "date": "2017-02-28",
          "equity": 173864.5715530214
        },
        {
          "date": "2017-03-31",
          "equity": 173864.5715530214
        },
        {
          "date": "2017-04-30",
          "equity": 180131.62016149657
        },
        {
          "date": "2017-05-31",
          "equity": 180131.62016149657
        },
        {
          "date": "2017-06-30",
          "equity": 180131.62016149657
        },
        {
          "date": "2017-07-31",
          "equity": 180131.62016149657
        },
        {
          "date": "2017-08-31",
          "equity": 183165.67092197284
        },
        {
          "date": "2017-09-30",
          "equity": 183165.67092197284
        },
        {
          "date": "2017-10-31",
          "equity": 183165.67092197284
        },
        {
          "date": "2017-11-30",
          "equity": 183165.67092197284
        },
        {
          "date": "2017-12-31",
          "equity": 183165.67092197284
        },
        {
          "date": "2018-01-31",
          "equity": 186635.13976782846
        },
        {
          "date": "2018-02-28",
          "equity": 173419.75230502442
        },
        {
          "date": "2018-03-31",
          "equity": 173419.75230502442
        },
        {
          "date": "2018-04-30",
          "equity": 173419.75230502442
        },
        {
          "date": "2018-05-31",
          "equity": 173419.75230502442
        },
        {
          "date": "2018-06-30",
          "equity": 173419.75230502442
        },
        {
          "date": "2018-07-31",
          "equity": 173419.75230502442
        },
        {
          "date": "2018-08-31",
          "equity": 176511.4664687766
        },
        {
          "date": "2018-09-30",
          "equity": 176511.4664687766
        },
        {
          "date": "2018-10-31",
          "equity": 174517.53065443411
        },
        {
          "date": "2018-11-30",
          "equity": 174517.53065443411
        },
        {
          "date": "2018-12-31",
          "equity": 174517.53065443411
        },
        {
          "date": "2019-01-31",
          "equity": 174517.53065443411
        },
        {
          "date": "2019-02-28",
          "equity": 174143.25715285397
        },
        {
          "date": "2019-03-31",
          "equity": 174143.25715285397
        },
        {
          "date": "2019-04-30",
          "equity": 174143.25715285397
        },
        {
          "date": "2019-05-31",
          "equity": 226666.9315891968
        },
        {
          "date": "2019-06-30",
          "equity": 226666.9315891968
        },
        {
          "date": "2019-07-31",
          "equity": 226666.9315891968
        },
        {
          "date": "2019-08-31",
          "equity": 226666.9315891968
        },
        {
          "date": "2019-09-30",
          "equity": 234853.6034369353
        },
        {
          "date": "2019-10-31",
          "equity": 234853.6034369353
        },
        {
          "date": "2019-11-30",
          "equity": 234427.07777592776
        },
        {
          "date": "2019-12-31",
          "equity": 233055.7741383613
        },
        {
          "date": "2020-01-31",
          "equity": 233055.7741383613
        },
        {
          "date": "2020-02-29",
          "equity": 366942.7151444864
        },
        {
          "date": "2020-03-31",
          "equity": 381568.0405878206
        },
        {
          "date": "2020-04-30",
          "equity": 381568.0405878206
        },
        {
          "date": "2020-05-31",
          "equity": 442842.0197180258
        },
        {
          "date": "2020-06-30",
          "equity": 460231.2231514392
        },
        {
          "date": "2020-07-31",
          "equity": 460231.2231514392
        },
        {
          "date": "2020-08-31",
          "equity": 478078.3381981219
        },
        {
          "date": "2020-09-30",
          "equity": 478078.3381981219
        },
        {
          "date": "2020-10-31",
          "equity": 468836.32802847435
        },
        {
          "date": "2020-11-30",
          "equity": 533281.8473725701
        },
        {
          "date": "2020-12-31",
          "equity": 544886.9329340992
        },
        {
          "date": "2021-01-31",
          "equity": 554461.1346268
        },
        {
          "date": "2021-02-28",
          "equity": 534000.8099715065
        },
        {
          "date": "2021-03-31",
          "equity": 534000.8099715065
        },
        {
          "date": "2021-04-30",
          "equity": 534000.8099715065
        },
        {
          "date": "2021-05-31",
          "equity": 534000.8099715065
        },
        {
          "date": "2021-06-30",
          "equity": 522607.05003812845
        },
        {
          "date": "2021-07-31",
          "equity": 522607.05003812845
        },
        {
          "date": "2021-08-31",
          "equity": 522607.05003812845
        },
        {
          "date": "2021-09-30",
          "equity": 522607.05003812845
        },
        {
          "date": "2021-10-31",
          "equity": 563593.5740538527
        },
        {
          "date": "2021-11-30",
          "equity": 563593.5740538527
        },
        {
          "date": "2021-12-31",
          "equity": 563593.5740538527
        },
        {
          "date": "2022-01-31",
          "equity": 563593.5740538527
        },
        {
          "date": "2022-02-28",
          "equity": 563593.5740538527
        },
        {
          "date": "2022-03-31",
          "equity": 563593.5740538527
        },
        {
          "date": "2022-04-30",
          "equity": 563593.5740538527
        },
        {
          "date": "2022-05-31",
          "equity": 563593.5740538527
        },
        {
          "date": "2022-06-30",
          "equity": 1014639.0055949781
        },
        {
          "date": "2022-07-31",
          "equity": 1063321.6620771766
        },
        {
          "date": "2022-08-31",
          "equity": 1090597.6101904179
        },
        {
          "date": "2022-09-30",
          "equity": 1604610.6321595786
        },
        {
          "date": "2022-10-31",
          "equity": 1604610.6321595786
        },
        {
          "date": "2022-11-30",
          "equity": 1604610.6321595786
        },
        {
          "date": "2022-12-31",
          "equity": 1603404.183897455
        },
        {
          "date": "2023-01-31",
          "equity": 1603404.183897455
        },
        {
          "date": "2023-02-28",
          "equity": 1631614.2130757412
        },
        {
          "date": "2023-03-31",
          "equity": 2199348.07914774
        },
        {
          "date": "2023-04-30",
          "equity": 2110891.0290945214
        },
        {
          "date": "2023-05-31",
          "equity": 2110891.0290945214
        },
        {
          "date": "2023-06-30",
          "equity": 2110891.0290945214
        },
        {
          "date": "2023-07-31",
          "equity": 2110891.0290945214
        },
        {
          "date": "2023-08-31",
          "equity": 2149340.9634044976
        },
        {
          "date": "2023-09-30",
          "equity": 2098950.567857826
        },
        {
          "date": "2023-10-31",
          "equity": 2098950.567857826
        },
        {
          "date": "2023-11-30",
          "equity": 2095115.5414905124
        },
        {
          "date": "2023-12-31",
          "equity": 2095115.5414905124
        },
        {
          "date": "2024-01-31",
          "equity": 2046110.5670907875
        },
        {
          "date": "2024-02-29",
          "equity": 2046110.5670907875
        },
        {
          "date": "2024-03-31",
          "equity": 2046110.5670907875
        },
        {
          "date": "2024-04-30",
          "equity": 2126532.508558135
        },
        {
          "date": "2024-05-31",
          "equity": 3079758.722961454
        },
        {
          "date": "2024-06-30",
          "equity": 3071195.5331467916
        },
        {
          "date": "2024-07-31",
          "equity": 3071195.5331467916
        },
        {
          "date": "2024-08-31",
          "equity": 3071195.5331467916
        },
        {
          "date": "2024-09-30",
          "equity": 3129179.8387446343
        },
        {
          "date": "2024-10-31",
          "equity": 3129179.8387446343
        },
        {
          "date": "2024-11-30",
          "equity": 3129179.8387446343
        },
        {
          "date": "2024-12-31",
          "equity": 3129179.8387446343
        },
        {
          "date": "2025-01-31",
          "equity": 3129179.8387446343
        },
        {
          "date": "2025-02-28",
          "equity": 4605506.019533512
        },
        {
          "date": "2025-03-31",
          "equity": 4631887.235732787
        },
        {
          "date": "2025-04-30",
          "equity": 4631887.235732787
        },
        {
          "date": "2025-05-31",
          "equity": 4631887.235732787
        },
        {
          "date": "2025-06-30",
          "equity": 4605747.5794751365
        },
        {
          "date": "2025-07-31",
          "equity": 4605747.5794751365
        },
        {
          "date": "2025-08-31",
          "equity": 4601772.9254457
        },
        {
          "date": "2025-09-30",
          "equity": 4840449.718701692
        },
        {
          "date": "2025-10-31",
          "equity": 4922892.502321705
        },
        {
          "date": "2025-11-30",
          "equity": 5007805.516265299
        },
        {
          "date": "2025-12-31",
          "equity": 5007805.516265299
        },
        {
          "date": "2026-01-31",
          "equity": 5007805.516265299
        },
        {
          "date": "2026-02-28",
          "equity": 5555157.350616754
        },
        {
          "date": "2026-03-31",
          "equity": 5555157.350616754
        },
        {
          "date": "2026-04-30",
          "equity": 5640972.996648491
        },
        {
          "date": "2026-05-31",
          "equity": 5640972.996648491
        },
        {
          "date": "2026-06-30",
          "equity": 6301761.0744246
        },
        {
          "date": "2026-07-31",
          "equity": 6422138.990694628
        }
      ],
      "metrics": {
        "trades": 165,
        "total_return_pct": 6322.138990694629,
        "cagr_pct": 31.979500760675727,
        "sharpe": 0.9268651142857525,
        "max_dd_pct": -8.477578228071469,
        "win_rate_pct": 63.63636363636363,
        "payoff": 3.3577476951468865,
        "expectancy_pct": 2.928928373394596,
        "avg_win_pct": 5.546520216495225,
        "avg_loss_pct": -1.6518573520315054,
        "profit_factor": 5.876058466507051
      },
      "last_close": 216.69200134277344,
      "last_date": "2026-07-08T00:00:00"
    }
  }
}